<Faction xmlns:meta="Editor">
	<Monsters>
		<Monster>
			<Name>RatSmall</Name>
			<Sprite meta:RefKey="Sprite">
				<Name>Oryx/uf_split/uf_heroes/rat</Name>
				<DrawActualSize>true</DrawActualSize>
			</Sprite>
			<Death meta:RefKey="Sprite">
				<Name>EffectSprites/Splatter/Splatter</Name>
				<UpdateRate>0.1</UpdateRate>
				<Colour>189,9,9,255</Colour>
			</Death>
			<AttackDelay>5</AttackDelay>
			<AttackSpeed>7</AttackSpeed>
			<HP>7</HP>
			<Rewards>
				<Item>RatSkin,1,50</Item>
				<Item>RatTail,1,50</Item>
			</Rewards>
			<AbilityRate>6</AbilityRate>
			<Abilities>
				<Ability>
					<TargetRestriction>BasicOrb</TargetRestriction>
					<Effect>Move</Effect>
				</Ability>
			</Abilities>
		</Monster>
		<Monster>
			<Name>RatGiant</Name>
			<Sprite meta:RefKey="Sprite">
				<Name>Oryx/uf_split/uf_heroes/rat_giant</Name>
				<DrawActualSize>true</DrawActualSize>
			</Sprite>
			<Death meta:RefKey="Sprite">
				<Name>EffectSprites/Splatter/Splatter</Name>
				<UpdateRate>0.1</UpdateRate>
				<Colour>189,9,9,255</Colour>
			</Death>
			<AttackDelay>4</AttackDelay>
			<AttackSpeed>6</AttackSpeed>
			<Size>2</Size>
			<HP>20</HP>
			<Rewards>
				<Item>RatSkin,2,50</Item>
				<Item>RatTail,2,50</Item>
			</Rewards>
			<AbilityRate>6</AbilityRate>
			<Abilities>
				<Ability>
					<TargetRestriction>BasicOrb</TargetRestriction>
					<Effect>Move</Effect>
				</Ability>
			</Abilities>
		</Monster>
	</Monsters>
</Faction>